spacecontrol/__init__.py
spacecontrol/__main__.py
spacecontrol/__version__.py
spacecontrol/sctl.py
spacecontrol/actions/DownloadAction.py
spacecontrol/actions/ExecAction.py
spacecontrol/actions/UploadAction.py
spacecontrol/actions/__init__.py
spacecontrol/configuration/__init__.py
spacecontrol/configuration/parser.py
spacecontrol/utilities/__init__.py
spacecontrol/utilities/logger.py
sctl-2020.0.4.dist-info/METADATA
sctl-2020.0.4.dist-info/WHEEL
sctl-2020.0.4.dist-info/entry_points.txt
sctl-2020.0.4.dist-info/top_level.txt
sctl-2020.0.4.dist-info/RECORD
