Metadata-Version: 2.1
Name: sctl
Version: 2020.0.4
Summary: A simple development environment manager.
Home-page: https://github.com/Lnk2past/space-control
Author: Lnk2past
License: MIT
Platform: UNKNOWN
Requires-Dist: fabric
Requires-Dist: pyyaml
